refal/__init__.py
refal/__version__.py
refal/algorithm.py
refal/ast.py
refal/built-in.type
refal/constants.py
refal/lexer_refal.py
refal/parser_refal.py
refal/position.py
refal/refalcheck.py
refal/test_file.py
refal/tokens.py
refal/utils.py
tests/__init__.py
tests/refal_test.py
tests/files/test1.ref
tests/files/test10.ref
tests/files/test11.ref
tests/files/test12.ref
tests/files/test13.ref
tests/files/test14.ref
tests/files/test14.type
tests/files/test15.ref
tests/files/test16.ref
tests/files/test17.ref
tests/files/test18.ref
tests/files/test18.type
tests/files/test19.ref
tests/files/test20.ref
tests/files/test20.type
tests/files/test21.ref
tests/files/test21.type
tests/files/test22.ref
tests/files/test22.type
tests/files/test23.ref
tests/files/test24.ref
tests/files/test25.ref
tests/files/test26.ref
tests/files/test27.ref
tests/files/test28.ref
tests/files/test29.ref
tests/files/test3.ref
tests/files/test30.ref
tests/files/test31.ref
tests/files/test32.ref
tests/files/test33.ref
tests/files/test34.ref
tests/files/test35.ref
tests/files/test36.ref
tests/files/test4.ref
tests/files/test40.ref
tests/files/test41.ref
tests/files/test42.ref
tests/files/test42.type
tests/files/test43.ref
tests/files/test44.ref
tests/files/test46.ref
tests/files/test47.ref
tests/files/test47.type
tests/files/test48.ref
tests/files/test48.type
tests/files/test49.ref
tests/files/test5.ref
tests/files/test50.ref
tests/files/test50.type
tests/files/test6.ref
tests/files/test7.ref
tests/files/test8.ref
refalchecker-2.2.0rc1.dist-info/LICENSE
refalchecker-2.2.0rc1.dist-info/METADATA
refalchecker-2.2.0rc1.dist-info/WHEEL
refalchecker-2.2.0rc1.dist-info/entry_points.txt
refalchecker-2.2.0rc1.dist-info/top_level.txt
refalchecker-2.2.0rc1.dist-info/RECORD
