Metadata-Version: 2.1
Name: refalchecker
Version: 2.2.0rc1
Summary: Calculating/Verifying format of functions in Refal-5
Home-page: https://github.com/runnerpeople/Refal5
Author: George Ivanov
Author-email: gosha8352@gmail.com
License: MIT
Platform: UNKNOWN
Classifier: License :: OSI Approved :: MIT License
Classifier: Programming Language :: Python
Classifier: Programming Language :: Python :: 3
Classifier: Programming Language :: Python :: 3.6
Classifier: Programming Language :: Python :: Implementation :: CPython
Classifier: Programming Language :: Python :: Implementation :: PyPy
Requires-Python: >=3.6.0
Requires-Dist: argparse
